{
    "date": "Nov 9, 2022 2:25:04 PM",
    "deviceDimensions": "1080x1920",
    "executionType": "Expected-Bottom_Up-",
    "topDown": false,
    "bottomUp": true,
    "noText": false,
    "expectedText": true,
    "unexpectedText": false,
    "contextFeatsEnabled": false,
    "contextFeatsDisabled": false,
    "executionNum": 1,
    "crash": false,
    "deviceName": "Android SDK built for x86",
    "elapsedTime": 501186,
    "orientation": 0,
    "mainActivity": "fr.free.nrw.commons.auth.LoginActivity",
    "androidVersion": "7.0",
    "steps": [],
    "app":
    {
        "name": "commons",
        "packageName": "fr.free.nrw.commons",
        "mainActivity": "fr.free.nrw.commons.auth.LoginActivity",
        "version": "2.7.2-debug",
        "apkPath": "/Users/junayed/Documents/NecessaryDocs/GeorgeMasonUniversity/Research/Projects/BugLocalization/FaultLocalizationCode/data/apks/132.apk"
    }
}